[
  {
    "inter": {
      "time": "2016-08-11T18:58:21.0051208484Z",
      "lat": 32.21479241,
      "fixFrac": 78.50051208484062,
      "lng": -101.52755824
    },
    "cross": {
      "inZone": [
        false,
        true
      ],
      "crossingPair": [
        {
          "time": "2016-08-11T18:58:16Z",
          "lat": 32.21406667,
          "fix": 78,
          "lng": -101.52765
        },
        {
          "time": "2016-08-11T18:58:26Z",
          "lat": 32.21551667,
          "fix": 79,
          "lng": -101.52746667
        }
      ]
    }
  },
  {
    "inter": {
      "time": "2016-08-11T19:15:42.40731620854Z",
      "lat": 32.29002027,
      "fixFrac": 183.14073162085492,
      "lng": -101.46185021
    },
    "cross": {
      "inZone": [
        true,
        false
      ],
      "crossingPair": [
        {
          "time": "2016-08-11T19:15:41Z",
          "lat": 32.28978333,
          "fix": 183,
          "lng": -101.46201667
        },
        {
          "time": "2016-08-11T19:15:51Z",
          "lat": 32.29146667,
          "fix": 184,
          "lng": -101.46083333
        }
      ]
    }
  },
  null,
  null,
  null
]
