{
  "waypoints": [
    {
      "lat": 32.22040097,
      "lng": -101.52223194
    },
    {
      "lat": 32.28760738,
      "lng": -101.45814918
    },
    {
      "lat": 32.4046303,
      "lng": -101.3433584
    },
    {
      "lat": 32.53001893,
      "lng": -101.70624967
    },
    {
      "lat": 32.74004686,
      "lng": -101.61604505
    },
    {
      "lat": 32.7589433,
      "lng": -101.91493328
    },
    {
      "lat": 32.7589433,
      "lng": -101.91493328
    }
  ],
  "flipSum": [
    "116.229222 km",
    "106.634555 km",
    "89.743633 km",
    "52.892208 km",
    "28.101046 km",
    "0.000000 km"
  ],
  "distance": "116.154314 km",
  "legsSum": [
    "9.594667 km",
    "26.485589 km",
    "63.337013 km",
    "88.128175 km",
    "116.229222 km",
    "116.229222 km"
  ],
  "legs": [
    "9.594667 km",
    "16.890922 km",
    "36.851425 km",
    "24.791162 km",
    "28.101046 km",
    "0.000000 km"
  ]
}
